autojs/__init__.py
autojs/__main__.py
autojs/autorunner.js
autojs/config.json
autojs/examples.py
autojs/filerunner.js
autojs/locator.js
autojs/recorder.js
autojs/runner.py
autojs/sensor.js
autojs/stringrunner.js
autoxjs-1.0.13.dist-info/METADATA
autoxjs-1.0.13.dist-info/WHEEL
autoxjs-1.0.13.dist-info/top_level.txt
autoxjs-1.0.13.dist-info/zip-safe
autoxjs-1.0.13.dist-info/RECORD
