Metadata-Version: 2.4
Name: AutoxJS
Version: 1.0.13
Summary: Launch Auto.js and AutoX.js scripts through Python in Termux.
Home-page: https://github.com/CannotLoadName/AutoxJS
Download-URL: https://github.com/CannotLoadName/AutoxJS/releases
Author: Enbuging
Author-email: electricfan@yeah.net
License: MIT License
Keywords: Auto.js,AutoX.js,Termux,Android,automation
Platform: Android
Platform: Linux
Dynamic: author
Dynamic: author-email
Dynamic: description
Dynamic: description-content-type
Dynamic: download-url
Dynamic: home-page
Dynamic: keywords
Dynamic: license
Dynamic: platform
Dynamic: summary
